robottools/__init__.py
robottools/rename.py
robottools/listeners/__init__.py
robottools/listeners/docstring.py
robottools/listeners/report_testlink.py
robottools/modifiers/__init__.py
robottools/modifiers/rename.py
robottools/reporters/__init__.py
robottools/reporters/testlink.py
robottools-0.4.0.dist-info/DESCRIPTION.rst
robottools-0.4.0.dist-info/METADATA
robottools-0.4.0.dist-info/RECORD
robottools-0.4.0.dist-info/WHEEL
robottools-0.4.0.dist-info/metadata.json
robottools-0.4.0.dist-info/top_level.txt
