Metadata-Version: 2.0
Name: robottools
Version: 0.4.0
Summary: UNKNOWN
Home-page: https://github.com/Brian-Williams/robottools
Author: Brian Williams
Author-email: briancmwilliams@gmail.com
License: UNKNOWN
Platform: UNKNOWN
Classifier: Development Status :: 3 - Alpha
Classifier: Intended Audience :: Developers
Classifier: Programming Language :: Python :: 2
Classifier: Programming Language :: Python :: 2.7
Classifier: Programming Language :: Python :: 3
Classifier: Programming Language :: Python :: 3.5
Classifier: Programming Language :: Python :: 3.6
Requires-Dist: robotframework (>=3.0.2)
Requires-Dist: testlink-api
Provides-Extra: test
Requires-Dist: flake8; extra == 'test'
Requires-Dist: pytest (>=2.9.0); extra == 'test'
